strangeworks_optimization/__init__.py
strangeworks_optimization/hybrid_optimizer.py
strangeworks_optimization/optimizer.py
strangeworks_optimization/py.typed
strangeworks_optimization-0.2.44.dist-info/METADATA
strangeworks_optimization-0.2.44.dist-info/WHEEL
strangeworks_optimization-0.2.44.dist-info/RECORD
