Metadata-Version: 2.4
Name: strangeworks-optimization
Version: 0.2.44
Summary: This SDK extends the Strangeworks SDK to provide access to the Strangeworks Optimization API.
Author-email: Strange Devs <hello@strangeworks.com>
License-Expression: Apache-2.0
Requires-Python: <3.14,>=3.11
Requires-Dist: strangeworks-optimization-models>=0.1.68
Requires-Dist: strangeworks<0.8.0,>=0.7.6
